simple_dvc_server/__init__.py
simple_dvc_server/_version.py
simple_dvc_server/server.py
simple_dvc_server-0.0.2.dist-info/LICENSE
simple_dvc_server-0.0.2.dist-info/METADATA
simple_dvc_server-0.0.2.dist-info/WHEEL
simple_dvc_server-0.0.2.dist-info/entry_points.txt
simple_dvc_server-0.0.2.dist-info/top_level.txt
simple_dvc_server-0.0.2.dist-info/zip-safe
simple_dvc_server-0.0.2.dist-info/RECORD
