Metadata-Version: 2.1
Name: simple-dvc-server
Version: 0.0.2
Summary: UNKNOWN
Home-page: UNKNOWN
License: UNKNOWN
Platform: UNKNOWN
Requires-Python: >3.5
Requires-Dist: RangeHTTPServer
Requires-Dist: loguru
